produttore_e_consumatore2/__init__.py
produttore_e_consumatore2-2.1.dist-info/LICENSE.md
produttore_e_consumatore2-2.1.dist-info/METADATA
produttore_e_consumatore2-2.1.dist-info/WHEEL
produttore_e_consumatore2-2.1.dist-info/top_level.txt
produttore_e_consumatore2-2.1.dist-info/zip-safe
produttore_e_consumatore2-2.1.dist-info/RECORD
