Metadata-Version: 2.1
Name: produttore-e-consumatore2
Version: 2.1
Summary: Multiprocessing
Home-page: https://github.com/CastellaniDavide/produttore_e_consumatore2
Author: CastellaniDavide
Author-email: help@castellanidavide.it
License: GNU
Platform: linux_distibution
Requires-Python: >=3.6
Requires-Dist: tabular-log
Requires-Dist: requests
Requires-Dist: programGUI (>=1.4)
Requires-Dist: psutil (>=5.8.0)
